py_simple_history/__init__.py
py_simple_history/main.py
py_simple_history/version.py
py_simple_history-0.0.1.dist-info/LICENSE
py_simple_history-0.0.1.dist-info/METADATA
py_simple_history-0.0.1.dist-info/WHEEL
py_simple_history-0.0.1.dist-info/top_level.txt
py_simple_history-0.0.1.dist-info/RECORD
