Metadata-Version: 2.1
Name: py-simple-history
Version: 0.0.1
Summary: A super simple history tracking class / mixin.
Author: Andrew Spangler
Author-email: Andrew Spangler <AndrewSpangler@users.noreply.github.com>
Project-URL: Homepage, https://github.com/AndrewSpangler/py_simple_history/
Project-URL: Bug Tracker, https://github.com/AndrewSpangler/py_simple_history//issues
Classifier: Development Status :: 1 - Planning
Classifier: Environment :: Console
Classifier: License :: OSI Approved :: GNU General Public License v3 or later (GPLv3+)
Classifier: Natural Language :: English
Classifier: Operating System :: OS Independent
Classifier: Programming Language :: Python :: 3
Classifier: Programming Language :: Python :: 3.8
Classifier: Programming Language :: Python :: 3.9
Classifier: Programming Language :: Python :: 3.10
Requires-Python: >=3.8
License-File: LICENSE
